InferGoKeggToGOBP.py
InferGoReactomeToGOBP.py
InferGoSlimToGOBP.py
VisPathways.py
enrichment.py
mergeDatabases.py
simpleTime.py
summarizePathwayHierarchy.py
treeGO.py
VisPathways-0.1.2.0.dist-info/LICENSE
VisPathways-0.1.2.0.dist-info/METADATA
VisPathways-0.1.2.0.dist-info/WHEEL
VisPathways-0.1.2.0.dist-info/top_level.txt
VisPathways-0.1.2.0.dist-info/RECORD
