Metadata-Version: 2.1
Name: VisPathways
Version: 0.1.2.0
Summary: A python and command line package to summarize and visualize pathway (gene set) hierarchies and enrichments.
Home-page: https://github.com/tommyfuu/FancyTaxonomies/blob/main/stableUsage
Author: Chenlian (Tom) Fu
Author-email: tfu@g.hmc.edu
License: UNKNOWN
Platform: UNKNOWN
Classifier: Programming Language :: Python :: 3
Classifier: Programming Language :: Python :: 3.6
Classifier: Programming Language :: Python :: 3.7
Classifier: License :: OSI Approved :: MIT License
Classifier: Operating System :: OS Independent
Requires-Python: >=3.6
License-File: LICENSE
Requires-Dist: pandas
Requires-Dist: numpy
Requires-Dist: scipy
Requires-Dist: ete3
Requires-Dist: PyQt5
Requires-Dist: matplotlib
